otpx/__init__.py
otpx/app.py
otpx/cli.py
otpx/constants.py
otpx/exceptions.py
otpx/helpers.py
otpx/screen.py
otpx-1.0.2.dist-info/METADATA
otpx-1.0.2.dist-info/WHEEL
otpx-1.0.2.dist-info/entry_points.txt
otpx-1.0.2.dist-info/top_level.txt
otpx-1.0.2.dist-info/RECORD
