Metadata-Version: 2.1
Name: otpx
Version: 1.0.2
Summary: Simple OTP Client
Home-page: http://github.com/meyt/otpx
Author: MeyT
License: MIT
Keywords: cli 2fa otp totp hotp
Platform: UNKNOWN
Classifier: Development Status :: 4 - Beta
Classifier: Intended Audience :: Developers
Classifier: License :: OSI Approved :: MIT License
Classifier: Operating System :: POSIX :: Linux
Classifier: Operating System :: Unix
Classifier: Programming Language :: Python :: 3.5
Classifier: Programming Language :: Python :: 3.6
Classifier: Programming Language :: Python :: 3.7
Classifier: Programming Language :: Python :: 3.8
Classifier: Programming Language :: Python :: 3.9
Classifier: Topic :: Security
Classifier: Topic :: Utilities
Classifier: Environment :: Console :: Curses
Classifier: Environment :: Console
Requires-Dist: pyotp (>=2.6.0)
Requires-Dist: pyperclip (>=1.8.2)
